llama_index/llms/openvino_genai/__init__.py
llama_index/llms/openvino_genai/base.py
llama_index_llms_openvino_genai-0.2.1.dist-info/METADATA
llama_index_llms_openvino_genai-0.2.1.dist-info/WHEEL
llama_index_llms_openvino_genai-0.2.1.dist-info/licenses/LICENSE
llama_index_llms_openvino_genai-0.2.1.dist-info/RECORD
